biscoint_api_python/__init__.py
biscoint_api_python-0.6.0.dist-info/LICENSE
biscoint_api_python-0.6.0.dist-info/METADATA
biscoint_api_python-0.6.0.dist-info/WHEEL
biscoint_api_python-0.6.0.dist-info/top_level.txt
biscoint_api_python-0.6.0.dist-info/RECORD
